MANIFEST.in
setup.py
docs/HISTORY.txt
src/dolmen/__init__.py
src/dolmen.forms.crud.egg-info/PKG-INFO
src/dolmen.forms.crud.egg-info/SOURCES.txt
src/dolmen.forms.crud.egg-info/dependency_links.txt
src/dolmen.forms.crud.egg-info/namespace_packages.txt
src/dolmen.forms.crud.egg-info/not-zip-safe
src/dolmen.forms.crud.egg-info/requires.txt
src/dolmen.forms.crud.egg-info/top_level.txt
src/dolmen/forms/__init__.py
src/dolmen/forms/crud/README.txt
src/dolmen/forms/crud/__init__.py
src/dolmen/forms/crud/addview.py
src/dolmen/forms/crud/configure.zcml
src/dolmen/forms/crud/crudforms.py
src/dolmen/forms/crud/customize.py
src/dolmen/forms/crud/events.py
src/dolmen/forms/crud/interfaces.py
src/dolmen/forms/crud/render.py
src/dolmen/forms/crud/utils.py
src/dolmen/forms/crud/locales/fr/LC_MESSAGES/dolmen.forms.crud.po
src/dolmen/forms/crud/render_templates/displaytemplate.pt
src/dolmen/forms/crud/tests/__init__.py
src/dolmen/forms/crud/tests/ftesting.zcml
src/dolmen/forms/crud/tests/test_all.py